Workbook

Sheet Cover Page
A1: DCF Valuation of Kaynes Technology India Ltd
A3: Prepared By:
A4: Sarthak Kapil

Sheet Company Overview
A1: COMPANY OVERVIEW
A3: Particular | B3: Details
A4: Company Name | B4: Kaynes Technology India Ltd
A5: Industry | B5: Electronics Manufacturing Services (EMS)
A6: Founded | B6: 1988
A7: Headquarters | B7: Mysuru, India
A8: Market Cap | B8: ₹21,006 Cr
A9: Revenue FY25 | B9: ₹3,626 Cr
A10: Net Profit FY25 | B10: ₹364 Cr
A11: Business Model | B11: End-to-end electronics manufacturing

Sheet Historical Financials
A1: HISTORICAL FINANCIALS
A3: Particulars | B3: FY21 | C3: FY22 | D3: FY23 | E3: FY24 | F3: FY25
A4: Revenue (₹ Cr) | B4: 706 | C4: 1125 | D4: 1706 | E4: 2007 | F4: 3626
A5: EBITDA (₹ Cr) | B5: 57 | C5: 99 | D5: 170 | E5: 220 | F5: 469
A6: EBITDA Margin (%) | B6: =B5/B4 -> 0.080736544 | C6: =C5/C4 -> 0.088 | D6: =D5/D4 -> 0.0996483 | E6: =E5/E4 -> 0.10961634 | F6: =F5/F4 -> 0.12934363
A7: Net Profit (₹ Cr) | B7: 29 | C7: 42 | D7: 95 | E7: 147 | F7: 364
A8: Net Margin (%) | B8: =B7/B4 -> 0.041076487 | C8: =C7/C4 -> 0.037333333 | D8: =D7/D4 -> 0.055685815 | E8: =E7/E4 -> 0.073243647 | F8: =F7/F4 -> 0.1003861
A9: Operating Cash Flow (₹ Cr) | B9: 43 | C9: 60 | D9: 118 | E9: 169 | F9: 372

Sheet Assumptions
A1: ASSUMPTIONS
A3: Assumption | B3: Value
A4: Revenue Growth Y1 | B4: 0.25
A5: Revenue Growth Y2 | B5: 0.22
A6: Revenue Growth Y3 | B6: 0.18
A7: Revenue Growth Y4 | B7: 0.15
A8: Revenue Growth Y5 | B8: 0.12
A9: FCF Margin | B9: 0.06
A10: WACC | B10: 0.12
A11: Terminal Growth | B11: 0.04

Sheet DCF valuations
A1: DCF VALUATIONS
A3: Particulars | B3: FY25 | C3: FY26 | D3: FY27 | E3: FY28 | F3: FY29 | G3: FY30
A4: Revenue | B4: 3626 | C4: =B4*(1+Assumptions!B4) -> 4532.5 | D4: =C4*(1+Assumptions!B5) -> 5529.65 | E4: =D4*(1+Assumptions!B6) -> 6524.987 | F4: =E4*(1+Assumptions!B7) -> 7503.735 | G4: =F4*(1+Assumptions!B8) -> 8404.1833
A5: Growth % | B5: - | C5: =Assumptions!B4 -> 0.25 | D5: =Assumptions!B5 -> 0.22 | E5: =Assumptions!B6 -> 0.18 | F5: =Assumptions!B7 -> 0.15 | G5: =Assumptions!B8 -> 0.12
A6: FCF Margin | B6: - | C6: =Assumptions!B9 -> 0.06 | D6: =Assumptions!B9 -> 0.06 | E6: =Assumptions!B9 -> 0.06 | F6: =Assumptions!B9 -> 0.06 | G6: =Assumptions!B9 -> 0.06
A7: Free Cash Flow | B7: - | C7: =C4*C6 -> 271.95 | D7: =D4*D6 -> 331.779 | E7: =E4*E6 -> 391.49922 | F7: =F4*F6 -> 450.2241 | G7: =G4*G6 -> 504.251
A8: Discount Factor | B8: - | C8: =1/(1+Assumptions!B10)^1 -> 0.89285714 | D8: =1/(1+Assumptions!B10)^2 -> 0.79719388 | E8: =1/(1+Assumptions!B10)^3 -> 0.71178025 | F8: =1/(1+Assumptions!B10)^4 -> 0.63551808 | G8: =1/(1+Assumptions!B10)^5 -> 0.56742686
A9: PV of FCF | B9: - | C9: =C7*C8 -> 242.8125 | D9: =D7*D8 -> 264.49219 | E9: =E7*E8 -> 278.66141 | F9: =F7*F8 -> 286.12556 | G9: =G7*G8 -> 286.12556
A12: Total PV of FCF | B12: =SUM(C9:G9) -> 1358.2172
A13: Terminal Growth Rate | B13: 0.04
A14: Terminal Value | B14: =(G7*(1+'DCF valuations'!B11))/(Assumptions!B10-Assumptions!B11) -> 6303.1374
A15: PV of Terminal Value | B15: =B14/(1+Assumptions!B10)^5 -> 3576.5695
A16: Enterprise Value | B16: =B12+B15 -> 4934.7867
A17: Current Market Cap | B17: 21006
A18: Difference | B18: =B16-B17 -> -16071.213
A19: Conclusion | B19: =IF(B16>B17,"UNDERVALUED","OVERVALUED") -> OVERVALUED
I26: Component | J26: Value
I27: PV of FCF | J27: 1358
I28: PV of Terminal Value | J28: 3720

Sheet Charts
A1: CHARTS

Sheet Executive Summary
A1: Executive Summary
A3: Metric | B3: Value
A4: Enterprise Value | B4: ₹5,078 Cr
A5: Market Cap | B5: ₹21,006 Cr
A6: Difference | B6: ₹15,928 Cr
A7: Conclusion | B7: OVERVALUED
A10: Key Findings
A11: Revenue projected to grow from ₹3,626 Cr to ₹8,404 Cr.
A12: Enterprise Value estimated at ₹5,078 Cr.
A13: Current Market Capitalization significantly exceeds intrinsic value.
A14: Stock appears overvalued under conservative assumptions.
A16: Recommendation: HOLD / AVOID
A18: Reason:
A19: The DCF-derived Enterprise Value of ₹5,078 Cr is significantly lower than the current market capitalization of ₹21,006 Cr, indicating that the stock appears overvalued under conservative assumptions.
